seq_practice/universal_reg/uni_reg.v
/* design desc:  A universal shift register can load parallel data, shift its content
left or right, or remain in the same state. It can perform parallel-to-serial operation (first
loading parallel input and then shifting) or serial-to-parallel operation (first shifting and
then retrieving parallel output).*/
module uni_reg
#(parameter N = 8)
(
    input wire clk, reset,
    input wire [1:0] data_ctrl,
    input wire [N-1:0] p_in,
    input wire s_in,
    output wire [N-1:0] p_out,
    output wire s_out
);
//params
localparam DO_NOTHING = 2'b00, SHIFT_LEFT = 2'b01, SHIFT_RIGHT = 2'b10, PARALLEL_LOAD = 2'b11;
//signals
reg [N-1:0] r_contents;
wire [N-1:0] r_next;

//register
always @(posedge clk or posedge reset)
    begin
        if(reset) r_contents <= 8'b0000_0000;
        else r_contents <= r_next;
    end

//next state logic
assign r_next = (data_ctrl==DO_NOTHING) ? r_contents : 
                (data_ctrl==SHIFT_RIGHT) ? {s_in, r_contents[N-1:1]} :
                (data_ctrl==SHIFT_LEFT) ? {r_contents[N-2:0], s_in} : 
                (data_ctrl==PARALLEL_LOAD) ? p_in :
                r_contents;

//output logic
assign p_out = r_contents;
assign s_out = r_contents[0];

endmodule

seq_practice/universal_reg/uni_reg_test.v
module uni_reg_test;
//signal decs
reg clk, reset, s_in;
reg [7:0] p_in;
reg [1:0] data_ctrl;
wire [7:0] p_out;
wire s_out;
localparam DO_NOTHING = 2'b00, SHIFT_LEFT = 2'b01, SHIFT_RIGHT = 2'b10, PARALLEL_LOAD = 2'b11;
//instantiation
uni_reg #(.N(8)) uut (.clk(clk), .reset(reset), .data_ctrl(data_ctrl), .p_in(p_in), .s_in(s_in), .p_out(p_out), .s_out(s_out));

//dumping
initial
    begin
        $dumpfile("unireg.vcd");
        $dumpvars(0,uni_reg_test);
        clk = 1'b0;
    end

//clock signal
always
    #5 clk = ~clk;

//inputs
initial
    begin
        @(negedge clk) reset = 1'b1;
        #1 reset = 1'b0;
        data_ctrl = PARALLEL_LOAD;
        p_in = 8'hAB;
        @(negedge clk) #1;
        data_ctrl = SHIFT_RIGHT;
        s_in = 1'b0;
        @(negedge clk) #1;
        data_ctrl = SHIFT_LEFT;
        s_in = 1'b1;
        @(negedge clk) #1;
        data_ctrl = DO_NOTHING;
        @(negedge clk) #1;
        data_ctrl = PARALLEL_LOAD;
        p_in = 8'hCD;
        @(negedge clk) #1;
        data_ctrl = SHIFT_RIGHT;
        s_in = 1'b0;
        @(negedge clk) #1;
        data_ctrl = SHIFT_RIGHT;
        s_in = 1'b1;
        @(negedge clk) #1;
        data_ctrl = SHIFT_RIGHT;
        s_in = 1'b0;
        #15 $finish;
    end

endmodule

seq_practice/universal_reg/unireg.vcd
$date
	Mon Jan 04 16:19:14 2021
$end
$version
	Icarus Verilog
$end
$timescale
	1s
$end
$scope module uni_reg_test $end
$var wire 1 ! s_out $end
$var wire 8 " p_out [7:0] $end
$var reg 1 # clk $end
$var reg 2 $ data_ctrl [1:0] $end
$var reg 8 % p_in [7:0] $end
$var reg 1 & reset $end
$var reg 1 ' s_in $end
$scope module uut $end
$var wire 1 # clk $end
$var wire 2 ( data_ctrl [1:0] $end
$var wire 8 ) p_in [7:0] $end
$var wire 8 * p_out [7:0] $end
$var wire 1 & reset $end
$var wire 1 ' s_in $end
$var wire 1 ! s_out $end
$var wire 8 + r_next [7:0] $end
$var reg 8 , r_contents [7:0] $end
$upscope $end
$upscope $end
$enddefinitions $end
#0
$dumpvars
bx ,
bx +
bx *
bx )
bx (
x'
x&
bx %
bx $
0#
bx "
x!
$end
#5
1#
#10
0!
b0 "
b0 *
b0 ,
1&
0#
#11
b10101011 +
b10101011 %
b10101011 )
b11 $
b11 (
0&
#15
1!
b10101011 "
b10101011 *
b10101011 ,
1#
#20
0#
#21
b1010101 +
0'
b10 $
b10 (
#25
b101010 +
b1010101 "
b1010101 *
b1010101 ,
1#
#30
0#
#31
b10101011 +
1'
b1 $
b1 (
#35
b1010111 +
b10101011 "
b10101011 *
b10101011 ,
1#
#40
0#
#41
b10101011 +
b0 $
b0 (
#45
1#
#50
0#
#51
b11001101 +
b11001101 %
b11001101 )
b11 $
b11 (
#55
b11001101 "
b11001101 *
b11001101 ,
1#
#60
0#
#61
b1100110 +
0'
b10 $
b10 (
#65
b110011 +
0!
b1100110 "
b1100110 *
b1100110 ,
1#
#70
0#
#71
b10110011 +
1'
#75
b11011001 +
1!
b10110011 "
b10110011 *
b10110011 ,
1#
#80
0#
#81
b1011001 +
0'
#85
b101100 +
b1011001 "
b1011001 *
b1011001 ,
1#
#90
0#
#95
b10110 +
0!
b101100 "
b101100 *
b101100 ,
1#
