fsm_practice/edge_detector/edge_moore.v
module edge_moore
(
    input wire clk, reset, level,
    output reg ticc
);
//params
localparam ZERO = 2'b00, EDGE = 2'b01, ONE = 2'b10;

//signal decl
reg [1:0] r_contents, r_next;

//state reg
always @(posedge clk or posedge reset)
    begin
        if(reset) r_contents <= 0;
        else r_contents <= r_next;
    end

//next state and output logic
always @(*)
        case(r_contents)
        ZERO :
            begin
                ticc = 1'b0;
                if(level)
                    r_next = EDGE;
                else 
                    r_next = ZERO;
            end
        EDGE :
            begin
                r_next = ONE;
                ticc = 1'b1;
            end
        ONE :
            begin
                ticc = 1'b0;
                if(level)
                    r_next = ONE;
                else 
                    r_next = ZERO;
            end
        default : r_next = r_contents;
        endcase

endmodule

fsm_practice/edge_detector/edge_moore_test.v
`timescale 1 ns/10 ps
module edge_moore_test;
//signals
reg clk, reset, level;
wire ticc;

//instantiation
edge_moore uut(.clk(clk), .level(level), .reset(reset), .ticc(ticc));

//dumping
initial
    begin
        $dumpfile("edge_moore.vcd");
        $dumpvars(0,edge_moore_test);
        clk = 1'b0;
        level = 1'b0;
    end
//clock
always
    #5 clk = ~clk;

//inputs
initial
    begin
        @(negedge clk) reset = 1'b1;
        #1 reset = 1'b0;
        level = 1'b1;
        #5 level = 1'b0;
        repeat(5) @(negedge clk);
        #1 level = 1'b1;
        #1 level = 1'b0;
        #20 $finish;
    end
endmodule

fsm_practice/edge_detector/edge_moore.vcd
$date
	Tue Jan 05 17:47:25 2021
$end
$version
	Icarus Verilog
$end
$timescale
	10ps
$end
$scope module edge_moore_test $end
$var wire 1 ! ticc $end
$var reg 1 " clk $end
$var reg 1 # level $end
$var reg 1 $ reset $end
$scope module uut $end
$var wire 1 " clk $end
$var wire 1 # level $end
$var wire 1 $ reset $end
$var reg 2 % r_contents [1:0] $end
$var reg 2 & r_next [1:0] $end
$var reg 1 ! ticc $end
$upscope $end
$upscope $end
$enddefinitions $end
#0
$dumpvars
bx &
bx %
x$
0#
0"
x!
$end
#500
1"
#1000
b0 &
0!
b0 %
1$
0"
#1100
b1 &
1#
0$
#1500
1!
b10 &
b1 %
1"
#1600
0#
#2000
0"
#2500
b0 &
0!
b10 %
1"
#3000
0"
#3500
b0 %
1"
#4000
0"
#4500
1"
#5000
0"
#5500
1"
#6000
0"
#6100
b1 &
1#
#6200
b0 &
0#
