seq_practice/universal_counter/uni_counter.v
/* desc: A universal binary counter is more versatile. It can count up
or down, pause, be loaded with a specific value, or be synchronously cleared. */
module uni_counter
#(parameter N = 8)
(
    input wire clk, reset, syn_clr,
    input wire [1:0] ctrl,
    input wire [N-1:0] data_in,
    output wire [N-1:0] count
);
//params
localparam COUNT_UP = 2'b00, COUNT_DOWN = 2'b01, PAUSE = 2'b10, LOAD = 2'b11;
//signals
reg [N-1:0] r_contents;
wire [N-1:0] r_next;

//register
always @(posedge clk or posedge reset)
    begin
        if(reset) r_contents = {N{1'b0}};
        else if(syn_clr) r_contents = {N{1'b0}};
        else r_contents = r_next;
    end

//next state logic
assign r_next = (ctrl==COUNT_UP) ? r_contents + 1 :
                (ctrl==COUNT_DOWN) ? r_contents - 1 :
                (ctrl==LOAD) ? data_in :
                (ctrl==PAUSE) ? r_contents :
                r_contents;

//output logic
assign count = r_contents;

endmodule

seq_practice/universal_counter/uni_counter_test.v
module uni_counter_test;
//signals
reg clk, reset, syn_clr;
reg [1:0] ctrl;
reg [7:0] data_in;
wire [7:0] count;
localparam COUNT_UP = 2'b00, COUNT_DOWN = 2'b01, PAUSE = 2'b10, LOAD = 2'b11;

//instantiation
uni_counter #(.N(8)) uut (.clk(clk), .reset(reset), .syn_clr(syn_clr), .ctrl(ctrl), .data_in(data_in), .count(count));

//dumping
initial
    begin
        $dumpfile("unicount.vcd");
        $dumpvars(0,uni_counter_test);
        clk = 1'b0;
    end

//clock signal
always  
    #5 clk = ~clk;

//inputs
initial
    begin
        @(negedge clk) reset = 1'b1;
        #1 reset = 1'b0;
        ctrl = COUNT_UP;
        @(negedge clk) #1;
        ctrl = COUNT_UP;
        @(negedge clk) #1;
        ctrl = COUNT_UP;
        @(negedge clk) #1;
        syn_clr = 1'b1;
        @(negedge clk) #1;
        syn_clr = 1'b0;
        ctrl = LOAD;
        data_in = 8'hAA;
        @(negedge clk) #1;
        ctrl = COUNT_DOWN;
        @(negedge clk) #1;
        ctrl = COUNT_DOWN;
        @(negedge clk) #1;
        ctrl = COUNT_DOWN;
        @(negedge clk) #1;
        ctrl = PAUSE;
        #15 $finish;
    end

endmodule

seq_practice/universal_counter/unicount.vcd
$date
	Mon Jan 04 17:16:14 2021
$end
$version
	Icarus Verilog
$end
$timescale
	1s
$end
$scope module uni_counter_test $end
$var wire 8 ! count [7:0] $end
$var reg 1 " clk $end
$var reg 2 # ctrl [1:0] $end
$var reg 8 $ data_in [7:0] $end
$var reg 1 % reset $end
$var reg 1 & syn_clr $end
$scope module uut $end
$var wire 1 " clk $end
$var wire 8 ' count [7:0] $end
$var wire 2 ( ctrl [1:0] $end
$var wire 8 ) data_in [7:0] $end
$var wire 1 % reset $end
$var wire 1 & syn_clr $end
$var wire 8 * r_next [7:0] $end
$var reg 8 + r_contents [7:0] $end
$upscope $end
$upscope $end
$enddefinitions $end
#0
$dumpvars
bx +
bx *
bx )
bx (
bx '
x&
x%
bx $
bx #
0"
bx !
$end
#5
1"
#10
b0 !
b0 '
b0 +
1%
0"
#11
b1 *
b0 #
b0 (
0%
#15
b10 *
b1 !
b1 '
b1 +
1"
#20
0"
#25
b11 *
b10 !
b10 '
b10 +
1"
#30
0"
#35
b100 *
b11 !
b11 '
b11 +
1"
#40
0"
#41
1&
#45
b1 *
b0 !
b0 '
b0 +
1"
#50
0"
#51
b10101010 *
b10101010 $
b10101010 )
b11 #
b11 (
0&
#55
b10101010 !
b10101010 '
b10101010 +
1"
#60
0"
#61
b10101001 *
b1 #
b1 (
#65
b10101000 *
b10101001 !
b10101001 '
b10101001 +
1"
#70
0"
#75
b10100111 *
b10101000 !
b10101000 '
b10101000 +
1"
#80
0"
#85
b10100110 *
b10100111 !
b10100111 '
b10100111 +
1"
#90
0"
#91
b10100111 *
b10 #
b10 (
