Combinational Examples/GCD/GCD.v
module datapath(
data_in,
loadA,
loadB,
sel1,
sel2,
sel_in,
G,
E,
L,
clk
);
input [15:0] data_in;
input loadA, loadB, sel1, sel2, sel_in, clk;
output G,E,L;
wire [15:0] wbus, Aout, Bout, MUXL_out, MUXR_out;
wire[15:0] Subout;
wire[15:0] SubA;
wire[15:0] SubB;

// controller CP (.done(done), .loadA(loadA), .loadB(loadB), .sel1(sel1), .sel2(sel2), .sel_in(sel_in), .G(G), .L(L), .E(E), .clk(clk));

pipo PIPOA(.in(wbus), .out(Aout), .load(loadA), .clk(clk));
pipo PIPOB(.in(wbus), .out(Bout), .load(loadB), .clk(clk));
compare COMP(.in1(Aout), .in2(Bout), .G(G), .E(E), .L(L));
MUX MUXL(.in1(Aout), .in2(Bout), .ctrl(sel1), .out(SubA));
MUX MUXR(.in1(Aout), .in2(Bout), .ctrl(sel2), .out(SubB));
subtractor SUB(.in1(SubA), .in2(SubB), .out(Subout));
MUX MUX_in(.in1(Subout), .in2(data_in), .ctrl(sel_in), .out(wbus));

endmodule

module controller(
done,
loadA,
loadB,
sel1,
sel2,
sel_in,
G,
E,
L,
clk,
start
);
input G,E,L, clk, start;
output reg done, sel1, sel2, sel_in, loadA, loadB;
reg[2:0] next_state;
reg[2:0] present_state = S0;

parameter S0 = 3'b000, S1 = 3'b001, S2 = 3'b010, S3 = 3'b011, S4 = 3'b100, S5 = 3'b101;
always @(posedge clk)
    present_state <= next_state;
always @(present_state)
    begin
       case (present_state)
    S0: begin
        #1;
        done = 0;
        sel_in = 1;
        loadA = 1;
        loadB = 0;
        if(start) next_state = S1;
    end
    S1: begin
        #1;
        done = 0;
        sel_in = 1;
        loadA = 0;
        loadB = 1;        
        next_state = S2;
    end
    S2: begin
        #1;
        if(G) begin
            sel_in = 0;
            sel1 = 0;
            sel2 = 1;
            #1;
            loadA = 1;
            loadB = 0;
            // #1;
            done = 0;
            next_state = S3;
        end
         if(L) begin
            sel_in = 0;
            sel1 = 1;
            sel2 = 0;
            #1;
            loadA = 0;
            loadB = 1;
            // #1;
            done = 0;
            next_state = S4;
        end
         if (E) begin
            // sel_in = 0;
            // sel1 = 0;
            // sel2 = 0;
            // #1;
            // loadA = 0;
            // loadB = 0;
            // #1;
            // done = 1;
            next_state = S5;            
        end 
    end
    S3: begin
        #1;
        if(G) begin
            sel_in = 0;
            sel1 = 0;
            sel2 = 1;
            #1;
            loadA = 1;
            loadB = 0;
            // #1;
            done = 0;
            next_state = S3;
        end
         if(L) begin
            sel_in = 0;
            sel1 = 1;
            sel2 = 0;
            #1;
            loadA = 0;
            loadB = 1;
            // #1;
            done = 0;
            next_state = S4;
        end
         if (E) begin
            // sel_in = 0;
            // sel1 = 0;
            // sel2 = 0;
            // #1;
            // loadA = 0;
            // loadB = 0;
            // #1;
            // done = 1;
            next_state = S5;            
        end   
    end
    S4: begin
        #1;
        if(G) begin
            sel_in = 0;
            sel1 = 0;
            sel2 = 1;
            #1;
            loadA = 1;
            loadB = 0;
            // #1;
            done = 0;
            next_state = S3;
        end
         if(L) begin
            sel_in = 0;
            sel1 = 1;
            sel2 = 0;
            #1;
            loadA = 0;
            loadB = 1;
            // #1;
            done = 0;
            next_state = S4;
        end
         if (E) begin
            sel_in = 0;
            sel1 = 0;
            sel2 = 0;
            // #1;
            // loadA = 0;
            // loadB = 0;
            // #1;
            // done = 1;
            next_state = S5;            
        end    
    end
    S5: begin
        // #1;
        done = 1;
        sel_in = 0;
        sel1 = 0;
        sel2 = 0;
        loadA = 0;
        loadB = 0;
        next_state = S5;
    end
    default: begin
        // sel_in = 0;
        // sel1 = 0;
        // sel2 = 0;
        loadA = 0;
        loadB = 0;
        // done = 0;   
        next_state = S0;     
    end
    endcase 
    end
endmodule
module pipo(
in,
out,
load,
clk
);
input [15:0] in;
input clk, load;
output reg [15:0] out;
always @(posedge clk)
begin
    if(load)
        begin
            out <= in;
        end
end
endmodule

module MUX(
in1,
in2,
ctrl,
out
);
input [15:0] in1,in2;
input ctrl;
output [15:0] out;
assign out = (ctrl)?in2:in1;
endmodule

module subtractor(
in1,
in2,
out
);
input [15:0] in1, in2;
output reg [15:0] out;
always @(in1,in2)
    out = in1 - in2;
endmodule

module compare(
in1,
in2,
G,
E,
L
);
input [15:0] in1,in2;
output G,E,L;
assign G = in1>in2?1:0;
assign E = in1==in2;
assign L = in1<in2?1:0;
endmodule

GCD/GCD_test.v
module test();
reg [15:0] data_in;
wire done;
reg clk;
controller CP(
done,
loadA,
loadB,
sel1,
sel2,
sel_in,
G,
E,
L,
clk,
start
);
datapath DP(
data_in,
loadA,
loadB,
sel1,
sel2,
sel_in,
G,
E,
L,
clk
);
assign start = 1;
initial 
    begin
        $dumpfile("GCD.vcd");
        $dumpvars(0, test);
        $monitor($time, " A = %16b, B = %16b, done = %b", DP.Aout, DP.Bout, CP.done);
        clk=1'b0;
        forever
            begin
                #5 clk=~clk;
            end
    end
initial
    begin
        #2 data_in = 6;
        #10 data_in = 4;
        #100 $finish;
    end

endmodule

Combinational Examples/GCD/GCD.vcd
$date
	Mon May 18 15:36:52 2020
$end
$version
	Icarus Verilog
$end
$timescale
	1s
$end
$scope module test $end
$var wire 1 ! start $end
$var wire 1 " sel_in $end
$var wire 1 # sel2 $end
$var wire 1 $ sel1 $end
$var wire 1 % loadB $end
$var wire 1 & loadA $end
$var wire 1 ' done $end
$var wire 1 ( L $end
$var wire 1 ) G $end
$var wire 1 * E $end
$var reg 1 + clk $end
$var reg 16 , data_in [15:0] $end
$scope module CP $end
$var wire 1 + clk $end
$var wire 1 ! start $end
$var wire 1 ( L $end
$var wire 1 ) G $end
$var wire 1 * E $end
$var reg 1 ' done $end
$var reg 1 & loadA $end
$var reg 1 % loadB $end
$var reg 3 - next_state [2:0] $end
$var reg 3 . present_state [2:0] $end
$var reg 1 $ sel1 $end
$var reg 1 # sel2 $end
$var reg 1 " sel_in $end
$upscope $end
$scope module DP $end
$var wire 1 + clk $end
$var wire 16 / data_in [15:0] $end
$var wire 1 & loadA $end
$var wire 1 % loadB $end
$var wire 1 $ sel1 $end
$var wire 1 # sel2 $end
$var wire 1 " sel_in $end
$var wire 16 0 wbus [15:0] $end
$var wire 16 1 Subout [15:0] $end
$var wire 16 2 SubB [15:0] $end
$var wire 16 3 SubA [15:0] $end
$var wire 1 ( L $end
$var wire 1 ) G $end
$var wire 1 * E $end
$var wire 16 4 Bout [15:0] $end
$var wire 16 5 Aout [15:0] $end
$scope module COMP $end
$var wire 16 6 in2 [15:0] $end
$var wire 16 7 in1 [15:0] $end
$var wire 1 ( L $end
$var wire 1 ) G $end
$var wire 1 * E $end
$upscope $end
$scope module MUXL $end
$var wire 1 $ ctrl $end
$var wire 16 8 out [15:0] $end
$var wire 16 9 in2 [15:0] $end
$var wire 16 : in1 [15:0] $end
$upscope $end
$scope module MUXR $end
$var wire 1 # ctrl $end
$var wire 16 ; out [15:0] $end
$var wire 16 < in2 [15:0] $end
$var wire 16 = in1 [15:0] $end
$upscope $end
$scope module MUX_in $end
$var wire 1 " ctrl $end
$var wire 16 > in2 [15:0] $end
$var wire 16 ? out [15:0] $end
$var wire 16 @ in1 [15:0] $end
$upscope $end
$scope module PIPOA $end
$var wire 1 + clk $end
$var wire 16 A in [15:0] $end
$var wire 1 & load $end
$var reg 16 B out [15:0] $end
$upscope $end
$scope module PIPOB $end
$var wire 1 + clk $end
$var wire 16 C in [15:0] $end
$var wire 1 % load $end
$var reg 16 D out [15:0] $end
$upscope $end
$scope module SUB $end
$var wire 16 E in1 [15:0] $end
$var wire 16 F in2 [15:0] $end
$var reg 16 G out [15:0] $end
$upscope $end
$upscope $end
$upscope $end
$enddefinitions $end
#0
$dumpvars
bx G
bx F
bx E
bx D
bx C
bx B
bx A
bx @
bx ?
bx >
bx =
bx <
bx ;
bx :
bx 9
bx 8
bx 7
bx 6
bx 5
bx 4
bx 3
bx 2
bx 1
bx 0
bx /
b0 .
bx -
bx ,
0+
x*
x)
x(
x'
x&
x%
x$
x#
x"
1!
$end
#1
b1 -
0%
1&
1"
0'
#2
b110 0
b110 ?
b110 A
b110 C
b110 ,
b110 /
b110 >
#5
b1 .
b110 5
b110 7
b110 :
b110 =
b110 B
1+
#6
b10 -
1%
0&
#10
0+
#12
b100 0
b100 ?
b100 A
b100 C
b100 ,
b100 /
b100 >
#15
0(
1)
b1x0 2
b1x0 ;
b1x0 F
b1x0 3
b1x0 8
b1x0 E
0*
b100 4
b100 6
b100 9
b100 <
b100 D
b10 .
1+
#16
b10 1
b10 @
b10 G
b100 2
b100 ;
b100 F
b110 3
b110 8
b110 E
b10 0
b10 ?
b10 A
b10 C
1#
0$
0"
#17
b11 -
0%
1&
#20
0+
#25
b1111111111111110 0
b1111111111111110 ?
b1111111111111110 A
b1111111111111110 C
b1111111111111110 1
b1111111111111110 @
b1111111111111110 G
1(
0)
b10 3
b10 8
b10 E
b11 .
b10 5
b10 7
b10 :
b10 =
b10 B
1+
#26
b10 0
b10 ?
b10 A
b10 C
b10 1
b10 @
b10 G
b10 2
b10 ;
b10 F
b100 3
b100 8
b100 E
0#
1$
#27
b100 -
1%
0&
#30
0+
#35
b0 0
b0 ?
b0 A
b0 C
b0 1
b0 @
b0 G
0(
b10 3
b10 8
b10 E
1*
b10 4
b10 6
b10 9
b10 <
b10 D
b100 .
1+
#36
b101 -
0$
#40
0+
#45
1)
0%
1'
b101 .
0*
b0 4
b0 6
b0 9
b0 <
b0 D
1+
